setup.py
PYNQKeithley/Keithley_DMM6500_VISA_Driver_Linux.py
PYNQKeithley/__init__.py
PYNQKeithley.egg-info/PKG-INFO
PYNQKeithley.egg-info/SOURCES.txt
PYNQKeithley.egg-info/dependency_links.txt
PYNQKeithley.egg-info/requires.txt
PYNQKeithley.egg-info/top_level.txt